textomatic/__init__.py
textomatic/app/__init__.py
textomatic/app/builder.py
textomatic/app/keys.py
textomatic/app/lexer.py
textomatic/app/style.py
textomatic/app/widgets.py
textomatic/context.py
textomatic/exceptions.py
textomatic/main.py
textomatic/model.py
textomatic/processor/__init__.py
textomatic/processor/common.py
textomatic/processor/inputs.py
textomatic/processor/macros.py
textomatic/processor/outputs.py
textomatic/processor/parser.py
textomatic/processor/process.py
textomatic/processor/registry.py
textomatic/text.py
textomatic-0.3.0.dist-info/entry_points.txt
textomatic-0.3.0.dist-info/LICENSE
textomatic-0.3.0.dist-info/WHEEL
textomatic-0.3.0.dist-info/METADATA
textomatic-0.3.0.dist-info/RECORD
