Metadata-Version: 2.1
Name: textomatic
Version: 0.3.0
Summary: Scratchpad for tabular data transformations, and then some
Home-page: https://github.com/dankilman/textomatic
License: MIT
Keywords: scratchpad,transformations,tabular-data
Author: Dan Kilman
Author-email: dankilman@gmail.com
Requires-Python: >=3.8,<4.0
Classifier: License :: OSI Approved :: MIT License
Classifier: Programming Language :: Python :: 3
Classifier: Programming Language :: Python :: 3.8
Requires-Dist: clevercsv (>=0.6.4,<0.7.0)
Requires-Dist: click (>=7.1.2,<8.0.0)
Requires-Dist: prompt-toolkit (>=3.0.7,<4.0.0)
Requires-Dist: pygments (>=2.7.1,<3.0.0)
Requires-Dist: pyparsing (>=2.4.7,<3.0.0)
Requires-Dist: pyperclip (>=1.8.0,<2.0.0)
Requires-Dist: tabulate (>=0.8.7,<0.9.0)
Project-URL: Documentation, https://github.com/dankilman/textomatic
Project-URL: Repository, https://github.com/dankilman/textomatic
